odoo/addons/web_favicon/README.rst
odoo/addons/web_favicon/__init__.py
odoo/addons/web_favicon/__manifest__.py
odoo/addons/web_favicon/controllers/__init__.py
odoo/addons/web_favicon/controllers/web_favicon.py
odoo/addons/web_favicon/i18n/ca.po
odoo/addons/web_favicon/i18n/da.po
odoo/addons/web_favicon/i18n/de.po
odoo/addons/web_favicon/i18n/es.po
odoo/addons/web_favicon/i18n/hr.po
odoo/addons/web_favicon/i18n/nl_NL.po
odoo/addons/web_favicon/i18n/pt_BR.po
odoo/addons/web_favicon/i18n/web_favicon.pot
odoo/addons/web_favicon/models/__init__.py
odoo/addons/web_favicon/models/res_company.py
odoo/addons/web_favicon/static/description/icon.png
odoo/addons/web_favicon/static/src/img/android-chrome-144x144.png
odoo/addons/web_favicon/static/src/img/android-chrome-192x192.png
odoo/addons/web_favicon/static/src/img/android-chrome-36x36.png
odoo/addons/web_favicon/static/src/img/android-chrome-48x48.png
odoo/addons/web_favicon/static/src/img/android-chrome-72x72.png
odoo/addons/web_favicon/static/src/img/android-chrome-96x96.png
odoo/addons/web_favicon/static/src/img/apple-touch-icon-114x114.png
odoo/addons/web_favicon/static/src/img/apple-touch-icon-120x120.png
odoo/addons/web_favicon/static/src/img/apple-touch-icon-144x144.png
odoo/addons/web_favicon/static/src/img/apple-touch-icon-152x152.png
odoo/addons/web_favicon/static/src/img/apple-touch-icon-180x180.png
odoo/addons/web_favicon/static/src/img/apple-touch-icon-57x57.png
odoo/addons/web_favicon/static/src/img/apple-touch-icon-60x60.png
odoo/addons/web_favicon/static/src/img/apple-touch-icon-72x72.png
odoo/addons/web_favicon/static/src/img/apple-touch-icon-76x76.png
odoo/addons/web_favicon/static/src/img/apple-touch-icon-precomposed.png
odoo/addons/web_favicon/static/src/img/apple-touch-icon.png
odoo/addons/web_favicon/static/src/img/browserconfig.xml
odoo/addons/web_favicon/static/src/img/favicon-16x16.png
odoo/addons/web_favicon/static/src/img/favicon-32x32.png
odoo/addons/web_favicon/static/src/img/favicon-96x96.png
odoo11_addon_web_favicon-11.0.1.0.1.dist-info/METADATA
odoo11_addon_web_favicon-11.0.1.0.1.dist-info/WHEEL
odoo11_addon_web_favicon-11.0.1.0.1.dist-info/top_level.txt
odoo11_addon_web_favicon-11.0.1.0.1.dist-info/RECORD
